{
  "total_count":1,
  "results":[
    {
      "identifiant_de_l_etablissement":"0341699M",
      "nom_etablissement":"Lycée de la Mer Paul Bousquet",
      "type_etablissement":"Lycée",
      "statut_public_prive":"Public",
      "adresse_1":"Rue des Cormorans",
      "adresse_2":"Pointe du Barrou",
      "adresse_3":null,
      "code_postal":"34207",
      "code_commune":"34301",
      "nom_commune":"Sète",
      "code_departement":"034",
      "code_academie":"11",
      "code_region":"76",
      "ecole_maternelle":null,
      "ecole_elementaire":null,
      "voie_generale":"0",
      "voie_technologique":"0",
      "voie_professionnelle":"1",
      "telephone":"04 67 51 63 63",
      "fax":"04 67 51 63 64",
      "web":"https://lyceedelamer.mon-ent-occitanie.fr/",
      "mail":"lyceemer-lr@developpement-durable.gouv.fr",
      "restauration":1,
      "hebergement":1,
      "ulis":0,
      "apprentissage":"1",
      "segpa":"0",
      "section_arts":"0",
      "section_cinema":"0",
      "section_theatre":"0",
      "section_sport":"0",
      "section_internationale":"0",
      "section_europeenne":"0",
      "lycee_agricole":"0",
      "lycee_militaire":"0",
      "lycee_des_metiers":"0",
      "post_bac":"1",
      "appartenance_education_prioritaire":null,
      "greta":"0",
      "siren_siret":"19341599900013",
      "nombre_d_eleves":null,
      "fiche_onisep":"https://www.onisep.fr/http/redirection/etablissement/slug/ENS.8307",
      "position":{
        "lon":3.6744903458750953,
        "lat":43.42339464589969
      },
      "type_contrat_prive":"SANS OBJET",
      "libelle_departement":"Hérault",
      "libelle_academie":"Montpellier",
      "libelle_region":"Occitanie",
      "coordx_origine":754645,
      "coordy_origine":6258487,
      "epsg_origine":"EPSG:2154",
      "nom_circonscription":null,
      "latitude":43.42339464589969,
      "longitude":3.6744903458750953,
      "precision_localisation":"Numéro de rue",
      "date_ouverture":"1987-09-01",
      "date_maj_ligne":"2025-09-26",
      "etat":"OUVERT",
      "ministere_tutelle":"MER",
      "multi_uai":0,
      "rpi_concentre":0,
      "rpi_disperse":null,
      "code_nature":320,
      "libelle_nature":"LYCEE PROFESSIONNEL",
      "code_type_contrat_prive":"99",
      "pial":null,
      "etablissement_mere":null,
      "type_rattachement_etablissement_mere":null,
      "code_circonscription":null,
      "code_zone_animation_pedagogique":null,
      "libelle_zone_animation_pedagogique":null,
      "code_bassin_formation":"11114",
      "libelle_bassin_formation":"BASSIN DE THAU"
    }
  ]
}
